{
 "version": 1,
 "catalog_id": "undercast",
 "schema": "schema/archive.schema.json",
 "title": "UNDERCAST — performers behind designed faces",
 "canonical_url": "https://bigbirdreturns.github.io/undercast/",
 "description": "A provenance-first field index of performers who vanish under prosthetics, masks, creature suits, performance capture, or an unseen voice.",
 "identifiers": {
  "record_pattern": "^UC-G?\\d+$",
  "record_key": "id",
  "never_reuse_ids": true
 },
 "canonical": {
  "records": {
   "path": "data/specimens.json",
   "bytes": 1008802,
   "sha256": "a390fa7ab59fcd4f5af13bbdf1476f45f4a5fa0208c50be1a11c6b249c19384b",
   "schema": "schema/specimen.schema.json",
   "count": 1078,
   "content_sha256": "b2fa0ca0dc346749bd3b979d5751b2fa08966d73c7c9a578ce1aa691f77f9f90"
  },
  "sources": {
   "path": "data/SOURCES.json",
   "bytes": 552485,
   "sha256": "ef13d6d9ac774af9df8507a212a0070b99539bbd86468d0cea942d4b74184bf3",
   "schema": "schema/source.schema.json",
   "count": 1078
  },
  "constellations": {
   "path": "data/constellations.json",
   "bytes": 168227,
   "sha256": "7e2d54b73e56d31b3e608e275e41e9717cac83d737b11df9266d6b36f2bb30cf",
   "schema": "schema/constellations.schema.json",
   "count": 3,
   "nodes": 163,
   "edges": 190
  },
  "ds9_changeling_census": {
   "path": "data/DS9-CHANGELING-CENSUS.json",
   "bytes": 8560,
   "sha256": "fbc5c340ca68bea25c3776fd12116a3ad6b2f94742de7631232dbcc3d9fc008d",
   "constellation_id": "constellation:ds9-changeling-performers"
  },
  "census_manifest": {
   "path": "data/CENSUS-MANIFEST.json",
   "bytes": 7252795,
   "sha256": "6fe4f606bfe4b50ff81b3f33a9c0e5e6a4c23c224acaa6a71c26c30aa9ada2da",
   "schema": "schema/census-manifest.schema.json"
  },
  "tombstones": {
   "path": "data/tombstones.json",
   "bytes": 605,
   "sha256": "7bfd86bd0752e971fb5433033cc0228ea9c41ace4741e5d3186fe0a62a743e71",
   "count": 2
  }
 },
 "schemas": {
  "archive": {
   "path": "schema/archive.schema.json",
   "bytes": 2013,
   "sha256": "6b2cfb7917b3806b48348423579d1aa05155a1bf295bfbbd67079c84c2c46a92",
   "media_type": "application/schema+json"
  },
  "specimen": {
   "path": "schema/specimen.schema.json",
   "bytes": 10189,
   "sha256": "2c4938cae082448f542a1136f5a8098a62d484c5c80967ded3c169ebec0bf604",
   "media_type": "application/schema+json"
  },
  "source": {
   "path": "schema/source.schema.json",
   "bytes": 4216,
   "sha256": "cc76056b87164ab2605ae7cc316ab5fbecb06ac1d87eef8d08e49c6839ddc2f8",
   "media_type": "application/schema+json"
  },
  "entities": {
   "path": "schema/entities.schema.json",
   "bytes": 1276,
   "sha256": "d3761ff1088536d48c8a067da6e4c4dec77ed5276733df058dab87d3dd95e082",
   "media_type": "application/schema+json"
  },
  "species": {
   "path": "schema/species.schema.json",
   "bytes": 4564,
   "sha256": "3e6a29ffd13d77286506681ded2e7284ac6e1f06d4082c55d7de661f0ea039d2",
   "media_type": "application/schema+json"
  },
  "species_vocabulary": {
   "path": "schema/species-vocabulary.schema.json",
   "bytes": 1149,
   "sha256": "5ecd42c96225a9db633c2ce66f0f54d28e990149e87f4570692b9634793e1d0c",
   "media_type": "application/schema+json"
  },
  "constellations": {
   "path": "schema/constellations.schema.json",
   "bytes": 3444,
   "sha256": "e008cf776e186c8d218433ea28704e6a5a82bfb1ef00582c047e4cc44d26b798",
   "media_type": "application/schema+json"
  },
  "census_manifest": {
   "path": "schema/census-manifest.schema.json",
   "bytes": 2451,
   "sha256": "383630bd6ea665ccdc465bea33ac5d9d05b91b5d9c5ad847ab19a890fc0fa5f7",
   "media_type": "application/schema+json"
  },
  "census_test": {
   "path": "schema/census-test.schema.json",
   "bytes": 2424,
   "sha256": "0705fe0920f4c7b20d673b07fa8097ab38225912c7548a3b8b5bc39792c6c527",
   "media_type": "application/schema+json"
  },
  "tombstones": {
   "path": "schema/tombstones.schema.json",
   "bytes": 1575,
   "sha256": "91170208b36b7702b47a8f084fc669ff8fca6a35799bf27f1545c4e3369d21b2",
   "media_type": "application/schema+json"
  }
 },
 "path_bases": {
  "contract_paths": "repository root",
  "shard_manifest_children": "data/"
 },
 "projections": {
  "lean_index": {
   "path": "data/index.json",
   "bytes": 317741,
   "sha256": "6f248f813fd098d9c087a03b367f9542f4329ef281dcdeae6fc7106e3f390d09"
  },
  "shard_manifest": {
   "path": "data/shard-manifest.json",
   "bytes": 769,
   "sha256": "d3593e0d1b315fe0bbc23134a8d1036c21b405c2f2b2afe6e8b87a7009b7728d",
   "count": 1078,
   "shards": [
    {
     "file": "shards/0000.json",
     "n": 1000,
     "bytes": 817011,
     "sha256": "9585a6bc9e87a89286dd7330fa3308f84e2a27b59cb94c3f561a080943d695c9"
    },
    {
     "file": "shards/0001.json",
     "n": 78,
     "bytes": 67952,
     "sha256": "2760790ac73e68ac6351761d691bb67abd0a42e364a125b8c455f6764a78000f"
    }
   ]
  },
  "entities": {
   "path": "data/entities.json",
   "bytes": 247494,
   "sha256": "de9fb68cc8864b05021631c4e4d6646ff630c15098d54bb579f68dfd22a4ce2d"
  },
  "species": {
   "path": "data/species.json",
   "bytes": 148791,
   "sha256": "c2ebdf3d501845de8536e7f78e74abd2ba66636b0d4cf42a8fcb526bad57335a"
  },
  "search": {
   "path": "data/search/manifest.json",
   "bytes": 6312,
   "sha256": "dc7e4a532ca417a2bd21169aeb3a1b687423dec14ea7a73d582402a524fbd3cd"
  },
  "media_live": {
   "path": "data/media-live.json",
   "bytes": 200618,
   "sha256": "deb5a5177cab8862be7abe8863110d37004f973d54051645d0ee96cca48ccacd"
  },
  "quality": {
   "path": "data/quality.json",
   "bytes": 624,
   "sha256": "e986a1f25e9fef70bc2a41ff8ea408578fa7791def40a54035396a5fdd4259b2"
  },
  "census": {
   "snapshot": {
    "path": "data/CENSUS.json",
    "bytes": 1636664,
    "sha256": "c755a271cc46e2da1af05c81d725a0f911a96e13143dc9c19efc9ac275e93396"
   },
   "coverage": {
    "path": "data/CENSUS-COVERAGE.json",
    "bytes": 2484739,
    "sha256": "0a9dbbf94f95208fee14ed2d87b351c61a8df556f363e4cd9f7483585870f390"
   },
   "gaps": {
    "path": "data/CENSUS-GAPS.json",
    "bytes": 820002,
    "sha256": "bb0db90df509f3bc74946877990c5fcd0d8fadadb5b4a53a95a91b9cccc6d35c"
   },
   "summary": {
    "path": "data/CENSUS-SUMMARY.json",
    "bytes": 185380,
    "sha256": "95d3e6166abf32278278e73ee2636a10f9cf982ece35e6e600c9913132987878"
   },
   "unresolved": {
    "path": "data/CENSUS-UNRESOLVED.json",
    "bytes": 2818043,
    "sha256": "b7063f0d7f7a8560087a0112f8fd45f1f479e06e33a93a2f0392374164ba8f84"
   },
   "exclusions": {
    "path": "data/CENSUS-EXCLUSIONS.json",
    "bytes": 374,
    "sha256": "b767d91dbb9434046d041e55773dfbce455dc8c8a3c23978b0b7ffa68aef1622"
   },
   "ferengi_test": {
    "path": "data/CENSUS-FERENGI-TEST.json",
    "bytes": 31931,
    "sha256": "ea77147c6e89317124c07e64e22c7363ce0ca314abdf14c28f81a4333ebb28c0"
   }
  }
 },
 "vocabularies": {
  "conditions": {
   "path": "data/vocabularies/conditions.json",
   "bytes": 1377,
   "sha256": "ed72ca51cff90ad7c3afc5c5487c6cd9f749eccbd1bcc407c9bb6227f6835c9a"
  },
  "species": {
   "path": "data/vocabularies/species.json",
   "bytes": 2188,
   "sha256": "c7dcd415d7f0582fda859f2e0fc2284ad36d6e65e1439c5b41f9bba2f6a9cbc3"
  }
 },
 "routes": {
  "record": "records/{id}/",
  "interactive_record": "recognition.html#{id}",
  "wall_record": "index.html#{id}",
  "filtered_wall": "index.html?{query}",
  "species_filtered_wall": "index.html?species={singular_label}",
  "constellation": "constellation.html?id={constellation_id}&node={node_id}",
  "recovery": "404.html",
  "retired_ids": "canonical.tombstones"
 },
 "discovery": {
  "robots": "robots.txt",
  "sitemap": "sitemap.xml",
  "dataset": "data/dataset.jsonld",
  "crawler_guide": "CRAWLERS.md"
 },
 "policies": {
  "truth": "Canonical records, image-source ledger and tombstones are maintained evidence. Every projection is disposable.",
  "evidence": "Do not promote inferred conditions or identities to fact. Evidence-scoped claims require a source URL.",
  "species": "Species navigation is generated only from maintained exact census categories and exact performer-role joins. Unknown performers and unresolved performance modes remain explicit.",
  "image_crop": "Fixed frames default to upper-center. Optional still.focus and portrait.focus are shared semantic overrides.",
  "cache": "Every cached artifact is disposable. sha256 and bytes describe the exact published UTF-8/LF payload.",
  "privacy": "No visitor profile, search history, or server-side session is collected."
 },
 "web_assets": [
  {
   "path": "index.html",
   "bytes": 76167,
   "sha256": "1a35351508feb21f6d6066744b2da6750729588421f795d8f7ebee68dd474c1b"
  },
  {
   "path": "recognition.html",
   "bytes": 57027,
   "sha256": "1784a2ba1dfd505d1025a47fa7c1d9d99586a547822c15c22e3798846c86aeef"
  },
  {
   "path": "coverage.html",
   "bytes": 14067,
   "sha256": "2d1441dac20cc62e2d684c1b5416f5d67fed4f3d0fb780886d5463a0f69354cc"
  },
  {
   "path": "constellation.html",
   "bytes": 11676,
   "sha256": "fd180ce8e5f98124b138832dfae387994398f83057b94e3d214ac5d0f89f406f"
  },
  {
   "path": "404.html",
   "bytes": 2877,
   "sha256": "d00c8bf405f284cb48f1958af36fb75f294c55d522dc70f40faaa4ff443e5c75"
  },
  {
   "path": "assets/site-shell.css",
   "bytes": 2342,
   "sha256": "8f9112fcd10103aeb7ae127f11ad75dcbde7d85b45bbb228eb13603491bee47b"
  },
  {
   "path": "assets/record-page.css",
   "bytes": 4266,
   "sha256": "f4bc92005b65fcf3a4ac881425db18479da3791d158c192cdcea2464dd880614"
  },
  {
   "path": "assets/coverage.css",
   "bytes": 3805,
   "sha256": "7704ad5857dc9524c6b952bd7b18469bba6f6b888ef736c5167f85582983d1d0"
  },
  {
   "path": "assets/constellation.css",
   "bytes": 6898,
   "sha256": "048e2876b01d162a6cebbe3e4a43c06388feaeba3721a8e390bc387960318262"
  }
 ]
}
